retailtree/__init__.py
retailtree/retailtree.py
retailtree/logics/__init__.py
retailtree/logics/overlap.py
retailtree/logics/right_left.py
retailtree/logics/top_bottom.py
retailtree/logics/vp_tree.py
retailtree/structs/__init__.py
retailtree/structs/annotation_struct.py
retailtree/utils/__init__.py
retailtree/utils/dist_func.py
tests/__init__.py
tests/test_neighbor.py
tests/test_tblr.py
tests/test_wa.py
retailtree-1.3.3.dist-info/METADATA
retailtree-1.3.3.dist-info/WHEEL
retailtree-1.3.3.dist-info/top_level.txt
retailtree-1.3.3.dist-info/RECORD
