Metadata-Version: 2.2
Name: retailtree
Version: 1.3.3
Requires-Dist: numpy
Dynamic: description
Dynamic: description-content-type
Dynamic: requires-dist
